gbrl/__init__.py
gbrl/gbrl_cpp.cpython-310-x86_64-linux-gnu.so
gbrl/common/__init__.py
gbrl/common/config.py
gbrl/common/utils.py
gbrl/include/dlpack/dlpack.h
gbrl/learners/__init__.py
gbrl/learners/actor_critic_learner.py
gbrl/learners/base.py
gbrl/learners/gbt_learner.py
gbrl/learners/multi_gbt_learner.py
gbrl/models/__init__.py
gbrl/models/actor.py
gbrl/models/actor_critic.py
gbrl/models/base.py
gbrl/models/critic.py
gbrl/models/gbt.py
gbrl/src/cpp/CMakeLists.txt
gbrl/src/cpp/binding.cpp
gbrl/src/cpp/config.h
gbrl/src/cpp/data_structs.cpp
gbrl/src/cpp/data_structs.h
gbrl/src/cpp/fitter.cpp
gbrl/src/cpp/fitter.h
gbrl/src/cpp/gbrl.cpp
gbrl/src/cpp/gbrl.h
gbrl/src/cpp/loss.cpp
gbrl/src/cpp/loss.h
gbrl/src/cpp/math_ops.cpp
gbrl/src/cpp/math_ops.h
gbrl/src/cpp/node.cpp
gbrl/src/cpp/node.h
gbrl/src/cpp/optimizer.cpp
gbrl/src/cpp/optimizer.h
gbrl/src/cpp/predictor.cpp
gbrl/src/cpp/predictor.h
gbrl/src/cpp/scheduler.cpp
gbrl/src/cpp/scheduler.h
gbrl/src/cpp/shap.cpp
gbrl/src/cpp/shap.h
gbrl/src/cpp/split_candidate_generator.cpp
gbrl/src/cpp/split_candidate_generator.h
gbrl/src/cpp/types.cpp
gbrl/src/cpp/types.h
gbrl/src/cpp/utils.cpp
gbrl/src/cpp/utils.h
gbrl/src/cuda/CMakeLists.txt
gbrl/src/cuda/cuda_fitter.cu
gbrl/src/cuda/cuda_fitter.h
gbrl/src/cuda/cuda_loss.cu
gbrl/src/cuda/cuda_loss.h
gbrl/src/cuda/cuda_predictor.cu
gbrl/src/cuda/cuda_predictor.h
gbrl/src/cuda/cuda_preprocess.cu
gbrl/src/cuda/cuda_preprocess.h
gbrl/src/cuda/cuda_types.cu
gbrl/src/cuda/cuda_types.h
gbrl/src/cuda/cuda_utils.cu
gbrl/src/cuda/cuda_utils.h
gbrl.libs/libcdt-2c22ec67.so.5.0.0
gbrl.libs/libcgraph-dca48271.so.6.0.0
gbrl.libs/libgomp-98b21ff3.so.1.0.0
gbrl.libs/libgvc-e51981ca.so.6.0.0
gbrl.libs/libltdl-38a07461.so.7.3.1
gbrl.libs/libpathplan-a80ac767.so.4.0.0
gbrl-1.1.6.dist-info/LICENSE
gbrl-1.1.6.dist-info/LICENSES.txt
gbrl-1.1.6.dist-info/METADATA
gbrl-1.1.6.dist-info/WHEEL
gbrl-1.1.6.dist-info/top_level.txt
gbrl-1.1.6.dist-info/RECORD
