Metadata-Version: 2.2
Name: gbrl
Version: 1.1.6
Summary: Gradient Boosted Trees for RL
Author: Benjamin Fuhrer, Chen Tessler, Gal Dalal
Author-email: Benjamin Fuhrer <bfuhrer@nvidia.com>, Chen Tessler <ctessler@nvidia.com>, Gal Dalal <galal@nvidia.com>
License: MIT
Project-URL: Homepage, https://github.com/NVlabs/gbrl
Project-URL: Documentation, https://nvlabs.github.io/gbrl/
Project-URL: Repository, https://github.com/NVlabs/gbrl
Classifier: Development Status :: 5 - Production/Stable
Classifier: Intended Audience :: Developers
Classifier: Intended Audience :: Science/Research
Classifier: License :: Other/Proprietary License
Classifier: Programming Language :: Python :: 3.9
Classifier: Programming Language :: Python :: 3.10
Classifier: Programming Language :: Python :: 3.11
Classifier: Programming Language :: Python :: 3.12
Classifier: Topic :: Software Development :: Libraries :: Python Modules
Classifier: Topic :: Scientific/Engineering :: Artificial Intelligence
Requires-Python: >=3.9
License-File: LICENSE
License-File: LICENSES.txt
Requires-Dist: pybind11[global]==2.13.1
Requires-Dist: numpy>=1.21.0
Requires-Dist: cmake>=3.18
Requires-Dist: torch>=1.13.1
Requires-Dist: scikit-learn>=1.5.0
Requires-Dist: scipy>=1.7.0
Requires-Dist: shap>=0.40.0
Requires-Dist: matplotlib>=3.5.0
Dynamic: author
Dynamic: license
